{
  "parent": "valleycraft:survival/craftingmat",
  "display": {
    "title": {
      "text": "Waste Not, Want Not"
    },
    "icon": {
      "item": "valleycraft:water_strainer"
    },
    "description": {
      "text": "Craft a Water Strainer"
    },
    "frame": "task"
  },
  "criteria": {
    "water_strainer": {
      "trigger": "minecraft:inventory_changed",
      "conditions": {
        "items": [
          {
            "items": [
              "valleycraft:water_strainer"
            ]
          }
        ]
      }
    }
  },
  "requirements": [
    [
      "water_strainer"
    ]
  ]
}