{
  "variants": {
    "facing=down,open=false": {
      "x": 180,
      "model": "valleycraft:block/crate"
    },
    "facing=down,open=true": {
      "x": 180,
      "model": "valleycraft:block/crate_open"
    },
    "facing=east,open=false": {
      "x": 90,
      "y": 90,
      "model": "valleycraft:block/crate"
    },
    "facing=east,open=true": {
      "x": 90,
      "y": 90,
      "model": "valleycraft:block/crate_open"
    },
    "facing=north,open=false": {
      "x": 90,
      "model": "valleycraft:block/crate"
    },
    "facing=north,open=true": {
      "x": 90,
      "model": "valleycraft:block/crate_open"
    },
    "facing=south,open=false": {
      "x": 90,
      "y": 180,
      "model": "valleycraft:block/crate"
    },
    "facing=south,open=true": {
      "x": 90,
      "y": 180,
      "model": "valleycraft:block/crate_open"
    },
    "facing=up,open=false": {
      "model": "valleycraft:block/crate"
    },
    "facing=up,open=true": {
      "model": "valleycraft:block/crate_open"
    },
    "facing=west,open=false": {
      "x": 90,
      "y": 270,
      "model": "valleycraft:block/crate"
    },
    "facing=west,open=true": {
      "x": 90,
      "y": 270,
      "model": "valleycraft:block/crate_open"
    }
  }
}